tkbanner/__init__.py
tkbanner/banner.py
tkbanner/extractor.py
tkbanner-0.1.0.dist-info/licenses/LICENSE
tkbanner-0.1.0.dist-info/METADATA
tkbanner-0.1.0.dist-info/WHEEL
tkbanner-0.1.0.dist-info/top_level.txt
tkbanner-0.1.0.dist-info/RECORD
