Metadata-Version: 2.4
Name: tkbanner
Version: 0.1.0
Summary: Animated video banner for tkinter
Author: Alexei54
Requires-Python: >=3.8
License-File: LICENSE
Requires-Dist: Pillow
Dynamic: license-file
